LICENSE
MANIFEST.in
README.rst
setup.py
gplearn/GP.py
gplearn/GPTool.py
gplearn/GP_SC.py
gplearn/__init__.py
gplearn/_program.py
gplearn/fitness.py
gplearn/functions.py
gplearn/genetic.py
gplearn/translateFn.py
gplearn/utils.py
gplearn_internal.egg-info/PKG-INFO
gplearn_internal.egg-info/SOURCES.txt
gplearn_internal.egg-info/dependency_links.txt
gplearn_internal.egg-info/not-zip-safe
gplearn_internal.egg-info/requires.txt
gplearn_internal.egg-info/top_level.txt