Metadata-Version: 2.1
Name: gplearn-internal
Version: 0.4.0
Summary: Genetic Programming in Python, with a scikit-learn inspired API
Home-page: https://github.com/LaGvidilo/gplearn
Author: Trevor Stephens & Rick Sanchez
Author-email: trev.stephens@gmail.com
License: new BSD
Platform: UNKNOWN
Classifier: Development Status :: 4 - Beta
Classifier: Environment :: Console
Classifier: Intended Audience :: Science/Research
Classifier: Intended Audience :: Developers
Classifier: License :: OSI Approved
Classifier: Topic :: Software Development
Classifier: Topic :: Scientific/Engineering
Classifier: Operating System :: Microsoft :: Windows
Classifier: Operating System :: Unix
Classifier: Operating System :: MacOS
Classifier: Programming Language :: Python
Classifier: Programming Language :: Python :: 3
Classifier: Programming Language :: Python :: 3.5
Classifier: Programming Language :: Python :: 3.6
Classifier: Programming Language :: Python :: 3.7
Provides-Extra: testing
Provides-Extra: docs
